asciibee/__init__.py
asciibee/constants.py
asciibee/image.py
asciibee/main.py
asciibee-0.3.2.dist-info/WHEEL
asciibee-0.3.2.dist-info/entry_points.txt
asciibee-0.3.2.dist-info/METADATA
asciibee-0.3.2.dist-info/RECORD
