Metadata-Version: 2.1
Name: asciibee
Version: 0.3.2
Summary: An image-to-ascii-art converter
Home-page: https://github.com/jameynakama/asciibee/
Author: Jamey Nakama
Author-email: nakamajamey@gmail.com
Requires-Python: >=3.10,<4.0
Classifier: Programming Language :: Python :: 3
Classifier: Programming Language :: Python :: 3.10
Classifier: Programming Language :: Python :: 3.11
Requires-Dist: Pillow (>=9.4,<10.0)
Requires-Dist: numpy (>=1.24.2,<2.0.0)
Project-URL: Repository, https://github.com/jameynakama/asciibee/
